cot/LMR.py
cot/__init__.py
cot/assignment.py
cot/optimaltransport.jar
cot/transport.py
PyCoOT-0.1.3.dist-info/LICENSE
PyCoOT-0.1.3.dist-info/METADATA
PyCoOT-0.1.3.dist-info/WHEEL
PyCoOT-0.1.3.dist-info/top_level.txt
PyCoOT-0.1.3.dist-info/RECORD
